timesetter/__init__.py
timesetter/__init__.pyi
timesetter/on_windows.dll
timesetter-1.7.dist-info/LICENSE
timesetter-1.7.dist-info/METADATA
timesetter-1.7.dist-info/WHEEL
timesetter-1.7.dist-info/top_level.txt
timesetter-1.7.dist-info/RECORD
