Metadata-Version: 2.1
Name: timesetter
Version: 1.7
Summary: A Python package to set system time regardless of operating system
Home-page: https://cunarist.com/timesetter
Author: cunarist
Author-email: cunarist@example.com
Project-URL: Bug Tracker, https://github.com/cunarist/timesetter/issues
Classifier: Programming Language :: Python :: 3
Classifier: License :: OSI Approved :: MIT License
Classifier: Operating System :: OS Independent
Requires-Python: >=3.6
License-File: LICENSE
